vaecompare/__init__.py
vaecompare/compare.py
vaecompare/estimate.py
vaecompare/htest.py
vaecompare/utils.py
vaecompare-1.0.dist-info/LICENSE
vaecompare-1.0.dist-info/METADATA
vaecompare-1.0.dist-info/WHEEL
vaecompare-1.0.dist-info/top_level.txt
vaecompare-1.0.dist-info/RECORD
